vitalserver/__init__.py
vitalserver/main.py
vitalserver-0.0.1.dist-info/METADATA
vitalserver-0.0.1.dist-info/WHEEL
vitalserver-0.0.1.dist-info/entry_points.txt
vitalserver-0.0.1.dist-info/top_level.txt
vitalserver-0.0.1.dist-info/RECORD
